dices/__init__.py
dices-0.0.1.dist-info/LICENSE
dices-0.0.1.dist-info/METADATA
dices-0.0.1.dist-info/WHEEL
dices-0.0.1.dist-info/top_level.txt
dices-0.0.1.dist-info/RECORD
