Metadata-Version: 2.1
Name: dices
Version: 0.0.1
Summary: A handful of dices
Home-page: https://github.com/skooda/pyDices
Author: V3L
Author-email: p@v3l.cz
License: UNKNOWN
Platform: UNKNOWN
Classifier: Programming Language :: Python :: 3
Classifier: License :: OSI Approved :: MIT License
Classifier: Operating System :: OS Independent
